{
    "type": "TileMatrixSetType",
    "title": "LINZ NZTM2000 Map Tile Grid",
    "abstract": "See https://www.linz.govt.nz/data/linz-data-service/guides-and-documentation/nztm2000-map-tile-service-schema",
    "id": "NZTM2000",
    "orderedAxes": [
        "Y",
        "X"
    ],
    "crs": "urn:ogc:def:crs:EPSG::2193",
    "tileMatrices": [
        {
            "id": "0",
            "scaleDenominator": 32000000,
            "pointOfOrigin": [
                10000000,
                -1000000
            ],
            "tileWidth": 256,
            "tileHeight": 256,
            "matrixWidth": 2,
            "matrixHeight": 4,
            "cellSize": 8960.0
        },
        {
            "id": "1",
            "scaleDenominator": 16000000,
            "pointOfOrigin": [
                10000000,
                -1000000
            ],
            "tileWidth": 256,
            "tileHeight": 256,
            "matrixWidth": 4,
            "matrixHeight": 8,
            "cellSize": 4480.0
        },
        {
            "id": "2",
            "scaleDenominator": 8000000,
            "pointOfOrigin": [
                10000000,
                -1000000
            ],
            "tileWidth": 256,
            "tileHeight": 256,
            "matrixWidth": 8,
            "matrixHeight": 16,
            "cellSize": 2240.0
        },
        {
            "id": "3",
            "scaleDenominator": 4000000,
            "pointOfOrigin": [
                10000000,
                -1000000
            ],
            "tileWidth": 256,
            "tileHeight": 256,
            "matrixWidth": 16,
            "matrixHeight": 32,
            "cellSize": 1120.0
        },
        {
            "id": "4",
            "scaleDenominator": 2000000,
            "pointOfOrigin": [
                10000000,
                -1000000
            ],
            "tileWidth": 256,
            "tileHeight": 256,
            "matrixWidth": 32,
            "matrixHeight": 64,
            "cellSize": 560.0
        },
        {
            "id": "5",
            "scaleDenominator": 1000000,
            "pointOfOrigin": [
                10000000,
                -1000000
            ],
            "tileWidth": 256,
            "tileHeight": 256,
            "matrixWidth": 64,
            "matrixHeight": 128,
            "cellSize": 280.0
        },
        {
            "id": "6",
            "scaleDenominator": 500000,
            "pointOfOrigin": [
                10000000,
                -1000000
            ],
            "tileWidth": 256,
            "tileHeight": 256,
            "matrixWidth": 128,
            "matrixHeight": 256,
            "cellSize": 140.0
        },
        {
            "id": "7",
            "scaleDenominator": 250000,
            "pointOfOrigin": [
                10000000,
                -1000000
            ],
            "tileWidth": 256,
            "tileHeight": 256,
            "matrixWidth": 256,
            "matrixHeight": 512,
            "cellSize": 70.0
        },
        {
            "id": "8",
            "scaleDenominator": 100000,
            "pointOfOrigin": [
                10000000,
                -1000000
            ],
            "tileWidth": 256,
            "tileHeight": 256,
            "matrixWidth": 640,
            "matrixHeight": 1280,
            "cellSize": 27.999999999999996
        },
        {
            "id": "9",
            "scaleDenominator": 50000,
            "pointOfOrigin": [
                10000000,
                -1000000
            ],
            "tileWidth": 256,
            "tileHeight": 256,
            "matrixWidth": 1280,
            "matrixHeight": 2560,
            "cellSize": 13.999999999999998
        },
        {
            "id": "10",
            "scaleDenominator": 25000,
            "pointOfOrigin": [
                10000000,
                -1000000
            ],
            "tileWidth": 256,
            "tileHeight": 256,
            "matrixWidth": 2560,
            "matrixHeight": 5120,
            "cellSize": 6.999999999999999
        },
        {
            "id": "11",
            "scaleDenominator": 10000,
            "pointOfOrigin": [
                10000000,
                -1000000
            ],
            "tileWidth": 256,
            "tileHeight": 256,
            "matrixWidth": 6400,
            "matrixHeight": 12800,
            "cellSize": 2.8
        },
        {
            "id": "12",
            "scaleDenominator": 5000,
            "pointOfOrigin": [
                10000000,
                -1000000
            ],
            "tileWidth": 256,
            "tileHeight": 256,
            "matrixWidth": 12800,
            "matrixHeight": 25600,
            "cellSize": 1.4
        },
        {
            "id": "13",
            "scaleDenominator": 2500,
            "pointOfOrigin": [
                10000000,
                -1000000
            ],
            "tileWidth": 256,
            "tileHeight": 256,
            "matrixWidth": 25600,
            "matrixHeight": 51200,
            "cellSize": 0.7
        },
        {
            "id": "14",
            "scaleDenominator": 1000,
            "pointOfOrigin": [
                10000000,
                -1000000
            ],
            "tileWidth": 256,
            "tileHeight": 256,
            "matrixWidth": 64000,
            "matrixHeight": 128000,
            "cellSize": 0.27999999999999997
        },
        {
            "id": "15",
            "scaleDenominator": 500,
            "pointOfOrigin": [
                10000000,
                -1000000
            ],
            "tileWidth": 256,
            "tileHeight": 256,
            "matrixWidth": 128000,
            "matrixHeight": 256000,
            "cellSize": 0.13999999999999999
        },
        {
            "id": "16",
            "scaleDenominator": 250,
            "pointOfOrigin": [
                10000000,
                -1000000
            ],
            "tileWidth": 256,
            "tileHeight": 256,
            "matrixWidth": 256000,
            "matrixHeight": 512000,
            "cellSize": 0.06999999999999999
        }
    ]
}